Metadata-Version: 2.1
Name: easywave
Version: 0.0.1
Summary: Easywave Library
Home-page: https://github.com/ferensw/python-easywave
Author: Ferens Wassink
License: MIT
Project-URL: Release notes, https://github.com/ferensw/python-easywave/releases
Keywords: easywave eldat rx09 domotica
Platform: UNKNOWN
Classifier: Development Status :: 3 - Alpha
Classifier: Intended Audience :: Developers
Classifier: License :: OSI Approved :: MIT License
Classifier: Programming Language :: Python :: 2.7
Classifier: Programming Language :: Python :: 3.6
Classifier: Programming Language :: Python :: 3.7
Classifier: Programming Language :: Python :: 3.8
Classifier: Programming Language :: Python :: 3.9
